[{ "id": 1, "name": "nobita", "age": 15 }, { "id": 2, "name": "doraemon", "age": 20 }, { "id": 3, "name": "jkdjkdd", "age": 40 }, { "id": 4, "name": "abcd", "age": 30 }, { "name": "dog", "age": "20" }, { "name": "iuu", "age": "20" }, { "name": "utywu", "age": "20" }, { "name": "rty", "age": "20" }, { "name": "rty", "age": "20" }, { "name": "r", "age": "20" }, { "name": "rd", "age": "20" }, { "name": "o", "age": "20" }, { "name": "x", "age": "20" }, { "name": "z", "age": "20" }, { "username": "tewyu", "email": "abc@abc.com" }, { "username": "tewyu", "email": "abc@abc.com" }, { "username": "mnvb", "email": "ty@rty.com", "password": "123" }, { "username": "kjhs", "email": "ty@rty.com", "password": "123" }, { "username": "zvcxv", "email": "pt@pt.com", "password": "123456" }]
